README.md
setup.py
cloudfront_edge_codes/__init__.py
cloudfront_edge_codes/version.py
cloudfront_edge_codes.egg-info/PKG-INFO
cloudfront_edge_codes.egg-info/SOURCES.txt
cloudfront_edge_codes.egg-info/dependency_links.txt
cloudfront_edge_codes.egg-info/entry_points.txt
cloudfront_edge_codes.egg-info/requires.txt
cloudfront_edge_codes.egg-info/top_level.txt
tests/__init__.py
tests/base.py
tests/test_parse_code.py