Metadata-Version: 1.1
Name: cloudfront-edge-codes
Version: 0.1.4
Summary: Cloudfront Edge Codes is a translator that returns information on the edge node based on its code. 
Home-page: https://github.com/heynemann/cloudfront-edge-codes
Author: Bernardo Heynemann
Author-email: heynemann@gmail.com
License: MIT
Keywords: cloudfront amazon aws edge codes translation parse
Platform: UNKNOWN
Classifier: Development Status :: 4 - Beta
Classifier: Intended Audience :: Developers
Classifier: License :: OSI Approved :: MIT License
Classifier: Natural Language :: English
Classifier: Operating System :: Unix
Classifier: Programming Language :: Python :: 2.7
Classifier: Programming Language :: Python :: 3.4
Classifier: Programming Language :: Python :: Implementation :: PyPy
Classifier: Operating System :: OS Independent
